nx_config/__init__.py
nx_config/cli.py
nx_config/config.py
nx_config/exceptions.py
nx_config/fill.py
nx_config/format.py
nx_config/path_resolution.py
nx_config/secret_string.py
nx_config/section.py
nx_config/url.py
nx_config/validation.py
nx_config/_core/__init__.py
nx_config/_core/config_meta.py
nx_config/_core/entry_to_text.py
nx_config/_core/fill_with_oracles.py
nx_config/_core/generate_template.py
nx_config/_core/iteration_utils.py
nx_config/_core/naming_utils.py
nx_config/_core/path_with_oracles.py
nx_config/_core/section_entry.py
nx_config/_core/section_meta.py
nx_config/_core/type_checks.py
nx_config/_core/typing_utils.py
nx_config/_core/unset.py
nx_config/_core/validator.py
nx_config/test_utils/__init__.py
nx_config/test_utils/updates.py
nx_config-0.2.0b5.dist-info/LICENSE
nx_config-0.2.0b5.dist-info/METADATA
nx_config-0.2.0b5.dist-info/WHEEL
nx_config-0.2.0b5.dist-info/top_level.txt
nx_config-0.2.0b5.dist-info/RECORD
